rtl/peripherals/audio_pwm.sv
module audio_pwm (
    input  logic        clk,
    input  logic        rst_n,
    input  logic        we_i,     // Write Enable from CPU
    input  logic [31:0] wdata_i,  // Data from CPU
    output logic        pwm_o     // To Physical Pin
);
    logic [7:0] sample_reg;
    logic [7:0] counter;

    // CPU Write Logic
    always_ff @(posedge clk or negedge rst_n) begin
        if (!rst_n) 
            sample_reg <= 8'h0;
        else if (we_i) 
            sample_reg <= wdata_i[7:0];
    end

    // PWM Generation
    always_ff @(posedge clk or negedge rst_n) begin
        if (!rst_n) begin
            counter <= 8'h0;
            pwm_o   <= 1'b0;
        end else begin
            counter <= counter + 1;
            pwm_o   <= (counter < sample_reg);
        end
    end
endmodule

rtl/peripherals/timer_apb.sv
module timer (
    input  logic        clk,
    input  logic        rst_n,
    input  logic        we_i,      // Write Enable from CPU
    input  logic [31:0] wdata_i,   // Data from CPU (Sets the threshold)
    output logic        irq        // The interrupt signal
);
    logic [31:0] count;
    logic [31:0] threshold_reg;

    // Register the threshold value when the CPU writes to it
    always_ff @(posedge clk or negedge rst_n) begin
        if (!rst_n) 
            threshold_reg <= 32'hFFFF; // Default slow rate
        else if (we_i)
            threshold_reg <= wdata_i;
    end

    // Counter logic
    always_ff @(posedge clk or negedge rst_n) begin
        if (!rst_n) begin
            count <= 0;
            irq   <= 0;
        end else begin
            if (count >= threshold_reg) begin
                count <= 0;
                irq   <= 1; // Trigger interrupt
            end else begin
                count <= count + 1;
                irq   <= 0;
            end
        end
    end
endmodule

rtl/memory/instr_mem.sv
module instr_mem (
    input  logic [31:0] addr,
    output logic [31:0] instr
);
    // 1024 word memory (4KB)
    logic [31:0] rom [0:1023];

    // Load the compiled HEX file (we will generate this next)
    initial begin
        $readmemh("dv/hex/firmware.hex", rom);
    end

    // Instruction alignment (RISC-V instructions are 4-byte aligned)
    assign instr = rom[addr[11:2]]; 
endmodule

rtl/core/pc.sv
module pc(
    input  logic        clk,
    input  logic        rst_n, //reset
    input  logic        irq, //Trigger input 
    input  logic [31:0] d,   //The normal next address usually pc+4
    output logic [31:0] q,   //The current address the cpu is executing
    output logic [31:0] mepc //Machine exception program counter
);

    always_ff @(posedge clk or negedge rst_n) begin
        if(!rst_n) begin
            q <= 32'h0;     //start at address 0 on power
        end else if (irq) begin 
    mepc <= d; 
    q <= 32'h20; 
end else begin
            q <= d;  //otherwise,just go to next normal instruction
        end
    end
endmodule

rtl/audio_soc_top.sv
module audio_soc_top (
    input  logic clk,
    input  logic rst_n,
    output logic audio_out
);
    // Interconnect Wires
    logic [31:0] pc_curr, pc_next;
    logic [31:0] instr;
    logic [31:0] alu_result, read_data2;
    logic        mem_we;
    
    // New Interrupt Signals
    logic        irq_signal; // Triggered by Timer
    logic [31:0] mepc_val;   // Saved PC during interrupt

    // 1. Program Counter (Updated with IRQ and MEPC)
    // Note: The logic for pc_next (pc+4 vs 0x20) should now move INSIDE the pc module
    // to handle the interrupt priority.
    pc u_pc (
        .clk(clk), 
        .rst_n(rst_n), 
        .d(pc_next),   // This usually comes from your branch/jump logic now
        .q(pc_curr),
        .irq(irq_signal), 
        .mepc(mepc_val)
    );

    // 2. Instruction Memory
    instr_mem u_imem (.addr(pc_curr), .instr(instr));

    // 3. Programmable Timer (The IRQ Source)
    // Maps to address 0x500 to set the "heartbeat" interval
    // 3. Programmable Timer (The IRQ Source)
    timer u_timer (
        .clk(clk),
        .rst_n(rst_n),
        .we_i(mem_we && (alu_result == 32'h500)),
        .wdata_i(read_data2),
        .irq(irq_signal)  // FIXED: Changed .irq_o to .irq to match timer.sv
    );

    // 4. Audio Peripheral (Memory Mapped to 0x400)
    audio_pwm u_audio (
        .clk(clk),
        .rst_n(rst_n),
        .we_i(mem_we && (alu_result == 32'h400)),
        .wdata_i(read_data2),
        .pwm_o(audio_out)
    );

    // 5. Basic Next-PC Logic (Simplified)
    // In a full RV32I, this would include Branch/Jump results.
    assign pc_next = pc_curr + 4;

endmodule

1.waveform.vcd
$version Generated by VerilatedVcd $end
$timescale 1ps $end
 $scope module TOP $end
  $var wire 1 , clk $end
  $var wire 1 - rst_n $end
  $var wire 1 . audio_out $end
  $scope module audio_soc_top $end
   $var wire 1 , clk $end
   $var wire 1 - rst_n $end
   $var wire 1 . audio_out $end
   $var wire 32 # pc_curr [31:0] $end
   $var wire 32 $ pc_next [31:0] $end
   $var wire 32 % instr [31:0] $end
   $var wire 32 / alu_result [31:0] $end
   $var wire 32 0 read_data2 [31:0] $end
   $var wire 1 1 mem_we $end
   $var wire 1 & irq_signal $end
   $var wire 32 ' mepc_val [31:0] $end
   $scope module u_audio $end
    $var wire 1 , clk $end
    $var wire 1 - rst_n $end
    $var wire 1 2 we_i $end
    $var wire 32 0 wdata_i [31:0] $end
    $var wire 1 . pwm_o $end
    $var wire 8 ( sample_reg [7:0] $end
    $var wire 8 ) counter [7:0] $end
   $upscope $end
   $scope module u_imem $end
    $var wire 32 # addr [31:0] $end
    $var wire 32 % instr [31:0] $end
   $upscope $end
   $scope module u_pc $end
    $var wire 1 , clk $end
    $var wire 1 - rst_n $end
    $var wire 1 & irq $end
    $var wire 32 $ d [31:0] $end
    $var wire 32 # q [31:0] $end
    $var wire 32 ' mepc [31:0] $end
   $upscope $end
   $scope module u_timer $end
    $var wire 1 , clk $end
    $var wire 1 - rst_n $end
    $var wire 1 3 we_i $end
    $var wire 32 0 wdata_i [31:0] $end
    $var wire 1 & irq $end
    $var wire 32 * count [31:0] $end
    $var wire 32 + threshold_reg [31:0] $end
   $upscope $end
  $upscope $end
 $upscope $end
$enddefinitions $end


#0
b00000000000000000000000000000000 #
b00000000000000000000000000000100 $
b01000000000000000000001010010011 %
0&
b00000000000000000000000000000000 '
b00000000 (
b00000000 )
b00000000000000000000000000000000 *
b00000000000000000000000000000000 +
1,
0-
0.
b00000000000000000000000000000000 /
b00000000000000000000000000000000 0
01
02
03
#1
0,
#2
b00000000000000001111111111111111 +
1,
#3
0,
#4
1,
#5
0,
#6
1,
#7
0,
#8
1,
#9
0,
#10
1,
#11
0,
#12
1,
#13
0,
#14
1,
#15
0,
#16
1,
#17
0,
#18
1,
#19
0,
#20
1,
#21
0,
1-
#22
b00000000000000000000000000000100 #
b00000000000000000000000000001000 $
b00001111111100000000001100010011 %
b00000001 )
b00000000000000000000000000000001 *
1,
#23
0,
#24
b00000000000000000000000000001000 #
b00000000000000000000000000001100 $
b00000000000000000000001110010011 %
b00000010 )
b00000000000000000000000000000010 *
1,
#25
0,
#26
b00000000000000000000000000001100 #
b00000000000000000000000000010000 $
b00000000011000101010000000100011 %
b00000011 )
b00000000000000000000000000000011 *
1,
#27
0,
#28
b00000000000000000000000000010000 #
b00000000000000000000000000010100 $
b00000110010000000000111000010011 %
b00000100 )
b00000000000000000000000000000100 *
1,
#29
0,
#30
b00000000000000000000000000010100 #
b00000000000000000000000000011000 $
b11111111111111100000111000010011 %
b00000101 )
b00000000000000000000000000000101 *
1,
#31
0,
#32
b00000000000000000000000000011000 #
b00000000000000000000000000011100 $
b11111110000011100001111011100011 %
b00000110 )
b00000000000000000000000000000110 *
1,
#33
0,
#34
b00000000000000000000000000011100 #
b00000000000000000000000000100000 $
b00000000011100101010000000100011 %
b00000111 )
b00000000000000000000000000000111 *
1,
#35
0,
#36
b00000000000000000000000000100000 #
b00000000000000000000000000100100 $
b00000110010000000000111000010011 %
b00001000 )
b00000000000000000000000000001000 *
1,
#37
0,
#38
b00000000000000000000000000100100 #
b00000000000000000000000000101000 $
b11111111111111100000111000010011 %
b00001001 )
b00000000000000000000000000001001 *
1,
#39
0,
#40
b00000000000000000000000000101000 #
b00000000000000000000000000101100 $
b11111110000011100001111011100011 %
b00001010 )
b00000000000000000000000000001010 *
1,
#41
0,
#42
b00000000000000000000000000101100 #
b00000000000000000000000000110000 $
b11111110000111111111000001101111 %
b00001011 )
b00000000000000000000000000001011 *
1,
#43
0,
#44
b00000000000000000000000000110000 #
b00000000000000000000000000110100 $
b00000000000000000000000000000000 %
b00001100 )
b00000000000000000000000000001100 *
1,
#45
0,
#46
b00000000000000000000000000110100 #
b00000000000000000000000000111000 $
b00001101 )
b00000000000000000000000000001101 *
1,
#47
0,
#48
b00000000000000000000000000111000 #
b00000000000000000000000000111100 $
b00001110 )
b00000000000000000000000000001110 *
1,
#49
0,
#50
b00000000000000000000000000111100 #
b00000000000000000000000001000000 $
b00001111 )
b00000000000000000000000000001111 *
1,
#51
0,
#52
b00000000000000000000000001000000 #
b00000000000000000000000001000100 $
b00010000 )
b00000000000000000000000000010000 *
1,
#53
0,
#54
b00000000000000000000000001000100 #
b00000000000000000000000001001000 $
b00010001 )
b00000000000000000000000000010001 *
1,
#55
0,
#56
b00000000000000000000000001001000 #
b00000000000000000000000001001100 $
b00010010 )
b00000000000000000000000000010010 *
1,
#57
0,
#58
b00000000000000000000000001001100 #
b00000000000000000000000001010000 $
b00010011 )
b00000000000000000000000000010011 *
1,
#59
0,
#60
b00000000000000000000000001010000 #
b00000000000000000000000001010100 $
b00010100 )
b00000000000000000000000000010100 *
1,
#61
0,
#62
b00000000000000000000000001010100 #
b00000000000000000000000001011000 $
b00010101 )
b00000000000000000000000000010101 *
1,
#63
0,
#64
b00000000000000000000000001011000 #
b00000000000000000000000001011100 $
b00010110 )
b00000000000000000000000000010110 *
1,
#65
0,
#66
b00000000000000000000000001011100 #
b00000000000000000000000001100000 $
b00010111 )
b00000000000000000000000000010111 *
1,
#67
0,
#68
b00000000000000000000000001100000 #
b00000000000000000000000001100100 $
b00011000 )
b00000000000000000000000000011000 *
1,
#69
0,
#70
b00000000000000000000000001100100 #
b00000000000000000000000001101000 $
b00011001 )
b00000000000000000000000000011001 *
1,
#71
0,
#72
b00000000000000000000000001101000 #
b00000000000000000000000001101100 $
b00011010 )
b00000000000000000000000000011010 *
1,
#73
0,
#74
b00000000000000000000000001101100 #
b00000000000000000000000001110000 $
b00011011 )
b00000000000000000000000000011011 *
1,
#75
0,
#76
b00000000000000000000000001110000 #
b00000000000000000000000001110100 $
b00011100 )
b00000000000000000000000000011100 *
1,
#77
0,
#78
b00000000000000000000000001110100 #
b00000000000000000000000001111000 $
b00011101 )
b00000000000000000000000000011101 *
1,
#79
0,
#80
b00000000000000000000000001111000 #
b00000000000000000000000001111100 $
b00011110 )
b00000000000000000000000000011110 *
1,
#81
0,
#82
b00000000000000000000000001111100 #
b00000000000000000000000010000000 $
b00011111 )
b00000000000000000000000000011111 *
1,
#83
0,
#84
b00000000000000000000000010000000 #
b00000000000000000000000010000100 $
b00100000 )
b00000000000000000000000000100000 *
1,
#85
0,
#86
b00000000000000000000000010000100 #
b00000000000000000000000010001000 $
b00100001 )
b00000000000000000000000000100001 *
1,
#87
0,
#88
b00000000000000000000000010001000 #
b00000000000000000000000010001100 $
b00100010 )
b00000000000000000000000000100010 *
1,
#89
0,
#90
b00000000000000000000000010001100 #
b00000000000000000000000010010000 $
b00100011 )
b00000000000000000000000000100011 *
1,
#91
0,
#92
b00000000000000000000000010010000 #
b00000000000000000000000010010100 $
b00100100 )
b00000000000000000000000000100100 *
1,
#93
0,
#94
b00000000000000000000000010010100 #
b00000000000000000000000010011000 $
b00100101 )
b00000000000000000000000000100101 *
1,
#95
0,
#96
b00000000000000000000000010011000 #
b00000000000000000000000010011100 $
b00100110 )
b00000000000000000000000000100110 *
1,
#97
0,
#98
b00000000000000000000000010011100 #
b00000000000000000000000010100000 $
b00100111 )
b00000000000000000000000000100111 *
1,
#99
0,
#100
b00000000000000000000000010100000 #
b00000000000000000000000010100100 $
b00101000 )
b00000000000000000000000000101000 *
1,
#101
0,
#102
b00000000000000000000000010100100 #
b00000000000000000000000010101000 $
b00101001 )
b00000000000000000000000000101001 *
1,
#103
0,
#104
b00000000000000000000000010101000 #
b00000000000000000000000010101100 $
b00101010 )
b00000000000000000000000000101010 *
1,
#105
0,
#106
b00000000000000000000000010101100 #
b00000000000000000000000010110000 $
b00101011 )
b00000000000000000000000000101011 *
1,
#107
0,
#108
b00000000000000000000000010110000 #
b00000000000000000000000010110100 $
b00101100 )
b00000000000000000000000000101100 *
1,
#109
0,
#110
b00000000000000000000000010110100 #
b00000000000000000000000010111000 $
b00101101 )
b00000000000000000000000000101101 *
1,
#111
0,
#112
b00000000000000000000000010111000 #
b00000000000000000000000010111100 $
b00101110 )
b00000000000000000000000000101110 *
1,
#113
0,
#114
b00000000000000000000000010111100 #
b00000000000000000000000011000000 $
b00101111 )
b00000000000000000000000000101111 *
1,
#115
0,
#116
b00000000000000000000000011000000 #
b00000000000000000000000011000100 $
b00110000 )
b00000000000000000000000000110000 *
1,
#117
0,
#118
b00000000000000000000000011000100 #
b00000000000000000000000011001000 $
b00110001 )
b00000000000000000000000000110001 *
1,
#119
0,
#120
b00000000000000000000000011001000 #
b00000000000000000000000011001100 $
b00110010 )
b00000000000000000000000000110010 *
1,
#121
0,
#122
b00000000000000000000000011001100 #
b00000000000000000000000011010000 $
b00110011 )
b00000000000000000000000000110011 *
1,
#123
0,
#124
b00000000000000000000000011010000 #
b00000000000000000000000011010100 $
b00110100 )
b00000000000000000000000000110100 *
1,
#125
0,
#126
b00000000000000000000000011010100 #
b00000000000000000000000011011000 $
b00110101 )
b00000000000000000000000000110101 *
1,
#127
0,
#128
b00000000000000000000000011011000 #
b00000000000000000000000011011100 $
b00110110 )
b00000000000000000000000000110110 *
1,
#129
0,
#130
b00000000000000000000000011011100 #
b00000000000000000000000011100000 $
b00110111 )
b00000000000000000000000000110111 *
1,
#131
0,
#132
b00000000000000000000000011100000 #
b00000000000000000000000011100100 $
b00111000 )
b00000000000000000000000000111000 *
1,
#133
0,
#134
b00000000000000000000000011100100 #
b00000000000000000000000011101000 $
b00111001 )
b00000000000000000000000000111001 *
1,
#135
0,
#136
b00000000000000000000000011101000 #
b00000000000000000000000011101100 $
b00111010 )
b00000000000000000000000000111010 *
1,
#137
0,
#138
b00000000000000000000000011101100 #
b00000000000000000000000011110000 $
b00111011 )
b00000000000000000000000000111011 *
1,
#139
0,
#140
b00000000000000000000000011110000 #
b00000000000000000000000011110100 $
b00111100 )
b00000000000000000000000000111100 *
1,
#141
0,
#142
b00000000000000000000000011110100 #
b00000000000000000000000011111000 $
b00111101 )
b00000000000000000000000000111101 *
1,
#143
0,
#144
b00000000000000000000000011111000 #
b00000000000000000000000011111100 $
b00111110 )
b00000000000000000000000000111110 *
1,
#145
0,
#146
b00000000000000000000000011111100 #
b00000000000000000000000100000000 $
b00111111 )
b00000000000000000000000000111111 *
1,
#147
0,
#148
b00000000000000000000000100000000 #
b00000000000000000000000100000100 $
b01000000 )
b00000000000000000000000001000000 *
1,
#149
0,
#150
b00000000000000000000000100000100 #
b00000000000000000000000100001000 $
b01000001 )
b00000000000000000000000001000001 *
1,
#151
0,
#152
b00000000000000000000000100001000 #
b00000000000000000000000100001100 $
b01000010 )
b00000000000000000000000001000010 *
1,
#153
0,
#154
b00000000000000000000000100001100 #
b00000000000000000000000100010000 $
b01000011 )
b00000000000000000000000001000011 *
1,
#155
0,
#156
b00000000000000000000000100010000 #
b00000000000000000000000100010100 $
b01000100 )
b00000000000000000000000001000100 *
1,
#157
0,
#158
b00000000000000000000000100010100 #
b00000000000000000000000100011000 $
b01000101 )
b00000000000000000000000001000101 *
1,
#159
0,
#160
b00000000000000000000000100011000 #
b00000000000000000000000100011100 $
b01000110 )
b00000000000000000000000001000110 *
1,
#161
0,
#162
b00000000000000000000000100011100 #
b00000000000000000000000100100000 $
b01000111 )
b00000000000000000000000001000111 *
1,
#163
0,
#164
b00000000000000000000000100100000 #
b00000000000000000000000100100100 $
b01001000 )
b00000000000000000000000001001000 *
1,
#165
0,
#166
b00000000000000000000000100100100 #
b00000000000000000000000100101000 $
b01001001 )
b00000000000000000000000001001001 *
1,
#167
0,
#168
b00000000000000000000000100101000 #
b00000000000000000000000100101100 $
b01001010 )
b00000000000000000000000001001010 *
1,
#169
0,
#170
b00000000000000000000000100101100 #
b00000000000000000000000100110000 $
b01001011 )
b00000000000000000000000001001011 *
1,
#171
0,
#172
b00000000000000000000000100110000 #
b00000000000000000000000100110100 $
b01001100 )
b00000000000000000000000001001100 *
1,
#173
0,
#174
b00000000000000000000000100110100 #
b00000000000000000000000100111000 $
b01001101 )
b00000000000000000000000001001101 *
1,
#175
0,
#176
b00000000000000000000000100111000 #
b00000000000000000000000100111100 $
b01001110 )
b00000000000000000000000001001110 *
1,
#177
0,
#178
b00000000000000000000000100111100 #
b00000000000000000000000101000000 $
b01001111 )
b00000000000000000000000001001111 *
1,
#179
0,
#180
b00000000000000000000000101000000 #
b00000000000000000000000101000100 $
b01010000 )
b00000000000000000000000001010000 *
1,
#181
0,
#182
b00000000000000000000000101000100 #
b00000000000000000000000101001000 $
b01010001 )
b00000000000000000000000001010001 *
1,
#183
0,
#184
b00000000000000000000000101001000 #
b00000000000000000000000101001100 $
b01010010 )
b00000000000000000000000001010010 *
1,
#185
0,
#186
b00000000000000000000000101001100 #
b00000000000000000000000101010000 $
b01010011 )
b00000000000000000000000001010011 *
1,
#187
0,
#188
b00000000000000000000000101010000 #
b00000000000000000000000101010100 $
b01010100 )
b00000000000000000000000001010100 *
1,
#189
0,
#190
b00000000000000000000000101010100 #
b00000000000000000000000101011000 $
b01010101 )
b00000000000000000000000001010101 *
1,
#191
0,
#192
b00000000000000000000000101011000 #
b00000000000000000000000101011100 $
b01010110 )
b00000000000000000000000001010110 *
1,
#193
0,
#194
b00000000000000000000000101011100 #
b00000000000000000000000101100000 $
b01010111 )
b00000000000000000000000001010111 *
1,
#195
0,
#196
b00000000000000000000000101100000 #
b00000000000000000000000101100100 $
b01011000 )
b00000000000000000000000001011000 *
1,
#197
0,
#198
b00000000000000000000000101100100 #
b00000000000000000000000101101000 $
b01011001 )
b00000000000000000000000001011001 *
1,
#199
0,
#200
b00000000000000000000000101101000 #
b00000000000000000000000101101100 $
b01011010 )
b00000000000000000000000001011010 *
1,
#201
0,
#202
b00000000000000000000000101101100 #
b00000000000000000000000101110000 $
b01011011 )
b00000000000000000000000001011011 *
1,
#203
0,
#204
b00000000000000000000000101110000 #
b00000000000000000000000101110100 $
b01011100 )
b00000000000000000000000001011100 *
1,
#205
0,
#206
b00000000000000000000000101110100 #
b00000000000000000000000101111000 $
b01011101 )
b00000000000000000000000001011101 *
1,
#207
0,
#208
b00000000000000000000000101111000 #
b00000000000000000000000101111100 $
b01011110 )
b00000000000000000000000001011110 *
1,
#209
0,
#210
b00000000000000000000000101111100 #
b00000000000000000000000110000000 $
b01011111 )
b00000000000000000000000001011111 *
1,
#211
0,
#212
b00000000000000000000000110000000 #
b00000000000000000000000110000100 $
b01100000 )
b00000000000000000000000001100000 *
1,
#213
0,
#214
b00000000000000000000000110000100 #
b00000000000000000000000110001000 $
b01100001 )
b00000000000000000000000001100001 *
1,
#215
0,
#216
b00000000000000000000000110001000 #
b00000000000000000000000110001100 $
b01100010 )
b00000000000000000000000001100010 *
1,
#217
0,
#218
b00000000000000000000000110001100 #
b00000000000000000000000110010000 $
b01100011 )
b00000000000000000000000001100011 *
1,
#219
0,
#220
b00000000000000000000000110010000 #
b00000000000000000000000110010100 $
b01100100 )
b00000000000000000000000001100100 *
1,
#221
0,
#222
b00000000000000000000000110010100 #
b00000000000000000000000110011000 $
b01100101 )
b00000000000000000000000001100101 *
1,
#223
0,
#224
b00000000000000000000000110011000 #
b00000000000000000000000110011100 $
b01100110 )
b00000000000000000000000001100110 *
1,
#225
0,
#226
b00000000000000000000000110011100 #
b00000000000000000000000110100000 $
b01100111 )
b00000000000000000000000001100111 *
1,
#227
0,
#228
b00000000000000000000000110100000 #
b00000000000000000000000110100100 $
b01101000 )
b00000000000000000000000001101000 *
1,
#229
0,
#230
b00000000000000000000000110100100 #
b00000000000000000000000110101000 $
b01101001 )
b00000000000000000000000001101001 *
1,
#231
0,
#232
b00000000000000000000000110101000 #
b00000000000000000000000110101100 $
b01101010 )
b00000000000000000000000001101010 *
1,
#233
0,
#234
b00000000000000000000000110101100 #
b00000000000000000000000110110000 $
b01101011 )
b00000000000000000000000001101011 *
1,
#235
0,
#236
b00000000000000000000000110110000 #
b00000000000000000000000110110100 $
b01101100 )
b00000000000000000000000001101100 *
1,
#237
0,
#238
b00000000000000000000000110110100 #
b00000000000000000000000110111000 $
b01101101 )
b00000000000000000000000001101101 *
1,
#239
0,
#240
b00000000000000000000000110111000 #
b00000000000000000000000110111100 $
b01101110 )
b00000000000000000000000001101110 *
1,
#241
0,
#242
b00000000000000000000000110111100 #
b00000000000000000000000111000000 $
b01101111 )
b00000000000000000000000001101111 *
1,
#243
0,
#244
b00000000000000000000000111000000 #
b00000000000000000000000111000100 $
b01110000 )
b00000000000000000000000001110000 *
1,
#245
0,
#246
b00000000000000000000000111000100 #
b00000000000000000000000111001000 $
b01110001 )
b00000000000000000000000001110001 *
1,
#247
0,
#248
b00000000000000000000000111001000 #
b00000000000000000000000111001100 $
b01110010 )
b00000000000000000000000001110010 *
1,
#249
0,
#250
b00000000000000000000000111001100 #
b00000000000000000000000111010000 $
b01110011 )
b00000000000000000000000001110011 *
1,
#251
0,
#252
b00000000000000000000000111010000 #
b00000000000000000000000111010100 $
b01110100 )
b00000000000000000000000001110100 *
1,
#253
0,
#254
b00000000000000000000000111010100 #
b00000000000000000000000111011000 $
b01110101 )
b00000000000000000000000001110101 *
1,
#255
0,
#256
b00000000000000000000000111011000 #
b00000000000000000000000111011100 $
b01110110 )
b00000000000000000000000001110110 *
1,
#257
0,
#258
b00000000000000000000000111011100 #
b00000000000000000000000111100000 $
b01110111 )
b00000000000000000000000001110111 *
1,
#259
0,
#260
b00000000000000000000000111100000 #
b00000000000000000000000111100100 $
b01111000 )
b00000000000000000000000001111000 *
1,
#261
0,
#262
b00000000000000000000000111100100 #
b00000000000000000000000111101000 $
b01111001 )
b00000000000000000000000001111001 *
1,
#263
0,
#264
b00000000000000000000000111101000 #
b00000000000000000000000111101100 $
b01111010 )
b00000000000000000000000001111010 *
1,
#265
0,
#266
b00000000000000000000000111101100 #
b00000000000000000000000111110000 $
b01111011 )
b00000000000000000000000001111011 *
1,
#267
0,
#268
b00000000000000000000000111110000 #
b00000000000000000000000111110100 $
b01111100 )
b00000000000000000000000001111100 *
1,
#269
0,
#270
b00000000000000000000000111110100 #
b00000000000000000000000111111000 $
b01111101 )
b00000000000000000000000001111101 *
1,
#271
0,
#272
b00000000000000000000000111111000 #
b00000000000000000000000111111100 $
b01111110 )
b00000000000000000000000001111110 *
1,
#273
0,
#274
b00000000000000000000000111111100 #
b00000000000000000000001000000000 $
b01111111 )
b00000000000000000000000001111111 *
1,
#275
0,
#276
b00000000000000000000001000000000 #
b00000000000000000000001000000100 $
b10000000 )
b00000000000000000000000010000000 *
1,
#277
0,
#278
b00000000000000000000001000000100 #
b00000000000000000000001000001000 $
b10000001 )
b00000000000000000000000010000001 *
1,
#279
0,
#280
b00000000000000000000001000001000 #
b00000000000000000000001000001100 $
b10000010 )
b00000000000000000000000010000010 *
1,
#281
0,
#282
b00000000000000000000001000001100 #
b00000000000000000000001000010000 $
b10000011 )
b00000000000000000000000010000011 *
1,
#283
0,
#284
b00000000000000000000001000010000 #
b00000000000000000000001000010100 $
b10000100 )
b00000000000000000000000010000100 *
1,
#285
0,
#286
b00000000000000000000001000010100 #
b00000000000000000000001000011000 $
b10000101 )
b00000000000000000000000010000101 *
1,
#287
0,
#288
b00000000000000000000001000011000 #
b00000000000000000000001000011100 $
b10000110 )
b00000000000000000000000010000110 *
1,
#289
0,
#290
b00000000000000000000001000011100 #
b00000000000000000000001000100000 $
b10000111 )
b00000000000000000000000010000111 *
1,
#291
0,
#292
b00000000000000000000001000100000 #
b00000000000000000000001000100100 $
b10001000 )
b00000000000000000000000010001000 *
1,
#293
0,
#294
b00000000000000000000001000100100 #
b00000000000000000000001000101000 $
b10001001 )
b00000000000000000000000010001001 *
1,
#295
0,
#296
b00000000000000000000001000101000 #
b00000000000000000000001000101100 $
b10001010 )
b00000000000000000000000010001010 *
1,
#297
0,
#298
b00000000000000000000001000101100 #
b00000000000000000000001000110000 $
b10001011 )
b00000000000000000000000010001011 *
1,
#299
0,
#300
b00000000000000000000001000110000 #
b00000000000000000000001000110100 $
b10001100 )
b00000000000000000000000010001100 *
1,
#301
0,
#302
b00000000000000000000001000110100 #
b00000000000000000000001000111000 $
b10001101 )
b00000000000000000000000010001101 *
1,
#303
0,
#304
b00000000000000000000001000111000 #
b00000000000000000000001000111100 $
b10001110 )
b00000000000000000000000010001110 *
1,
#305
0,
#306
b00000000000000000000001000111100 #
b00000000000000000000001001000000 $
b10001111 )
b00000000000000000000000010001111 *
1,
#307
0,
#308
b00000000000000000000001001000000 #
b00000000000000000000001001000100 $
b10010000 )
b00000000000000000000000010010000 *
1,
#309
0,
#310
b00000000000000000000001001000100 #
b00000000000000000000001001001000 $
b10010001 )
b00000000000000000000000010010001 *
1,
#311
0,
#312
b00000000000000000000001001001000 #
b00000000000000000000001001001100 $
b10010010 )
b00000000000000000000000010010010 *
1,
#313
0,
#314
b00000000000000000000001001001100 #
b00000000000000000000001001010000 $
b10010011 )
b00000000000000000000000010010011 *
1,
#315
0,
#316
b00000000000000000000001001010000 #
b00000000000000000000001001010100 $
b10010100 )
b00000000000000000000000010010100 *
1,
#317
0,
#318
b00000000000000000000001001010100 #
b00000000000000000000001001011000 $
b10010101 )
b00000000000000000000000010010101 *
1,
#319
0,
#320
b00000000000000000000001001011000 #
b00000000000000000000001001011100 $
b10010110 )
b00000000000000000000000010010110 *
1,
#321
0,
#322
b00000000000000000000001001011100 #
b00000000000000000000001001100000 $
b10010111 )
b00000000000000000000000010010111 *
1,
#323
0,
#324
b00000000000000000000001001100000 #
b00000000000000000000001001100100 $
b10011000 )
b00000000000000000000000010011000 *
1,
#325
0,
#326
b00000000000000000000001001100100 #
b00000000000000000000001001101000 $
b10011001 )
b00000000000000000000000010011001 *
1,
#327
0,
#328
b00000000000000000000001001101000 #
b00000000000000000000001001101100 $
b10011010 )
b00000000000000000000000010011010 *
1,
#329
0,
#330
b00000000000000000000001001101100 #
b00000000000000000000001001110000 $
b10011011 )
b00000000000000000000000010011011 *
1,
#331
0,
#332
b00000000000000000000001001110000 #
b00000000000000000000001001110100 $
b10011100 )
b00000000000000000000000010011100 *
1,
#333
0,
#334
b00000000000000000000001001110100 #
b00000000000000000000001001111000 $
b10011101 )
b00000000000000000000000010011101 *
1,
#335
0,
#336
b00000000000000000000001001111000 #
b00000000000000000000001001111100 $
b10011110 )
b00000000000000000000000010011110 *
1,
#337
0,
#338
b00000000000000000000001001111100 #
b00000000000000000000001010000000 $
b10011111 )
b00000000000000000000000010011111 *
1,
#339
0,
#340
b00000000000000000000001010000000 #
b00000000000000000000001010000100 $
b10100000 )
b00000000000000000000000010100000 *
1,
#341
0,
#342
b00000000000000000000001010000100 #
b00000000000000000000001010001000 $
b10100001 )
b00000000000000000000000010100001 *
1,
#343
0,
#344
b00000000000000000000001010001000 #
b00000000000000000000001010001100 $
b10100010 )
b00000000000000000000000010100010 *
1,
#345
0,
#346
b00000000000000000000001010001100 #
b00000000000000000000001010010000 $
b10100011 )
b00000000000000000000000010100011 *
1,
#347
0,
#348
b00000000000000000000001010010000 #
b00000000000000000000001010010100 $
b10100100 )
b00000000000000000000000010100100 *
1,
#349
0,
#350
b00000000000000000000001010010100 #
b00000000000000000000001010011000 $
b10100101 )
b00000000000000000000000010100101 *
1,
#351
0,
#352
b00000000000000000000001010011000 #
b00000000000000000000001010011100 $
b10100110 )
b00000000000000000000000010100110 *
1,
#353
0,
#354
b00000000000000000000001010011100 #
b00000000000000000000001010100000 $
b10100111 )
b00000000000000000000000010100111 *
1,
#355
0,
#356
b00000000000000000000001010100000 #
b00000000000000000000001010100100 $
b10101000 )
b00000000000000000000000010101000 *
1,
#357
0,
#358
b00000000000000000000001010100100 #
b00000000000000000000001010101000 $
b10101001 )
b00000000000000000000000010101001 *
1,
#359
0,
#360
b00000000000000000000001010101000 #
b00000000000000000000001010101100 $
b10101010 )
b00000000000000000000000010101010 *
1,
#361
0,
#362
b00000000000000000000001010101100 #
b00000000000000000000001010110000 $
b10101011 )
b00000000000000000000000010101011 *
1,
#363
0,
#364
b00000000000000000000001010110000 #
b00000000000000000000001010110100 $
b10101100 )
b00000000000000000000000010101100 *
1,
#365
0,
#366
b00000000000000000000001010110100 #
b00000000000000000000001010111000 $
b10101101 )
b00000000000000000000000010101101 *
1,
#367
0,
#368
b00000000000000000000001010111000 #
b00000000000000000000001010111100 $
b10101110 )
b00000000000000000000000010101110 *
1,
#369
0,
#370
b00000000000000000000001010111100 #
b00000000000000000000001011000000 $
b10101111 )
b00000000000000000000000010101111 *
1,
#371
0,
#372
b00000000000000000000001011000000 #
b00000000000000000000001011000100 $
b10110000 )
b00000000000000000000000010110000 *
1,
#373
0,
#374
b00000000000000000000001011000100 #
b00000000000000000000001011001000 $
b10110001 )
b00000000000000000000000010110001 *
1,
#375
0,
#376
b00000000000000000000001011001000 #
b00000000000000000000001011001100 $
b10110010 )
b00000000000000000000000010110010 *
1,
#377
0,
#378
b00000000000000000000001011001100 #
b00000000000000000000001011010000 $
b10110011 )
b00000000000000000000000010110011 *
1,
#379
0,
#380
b00000000000000000000001011010000 #
b00000000000000000000001011010100 $
b10110100 )
b00000000000000000000000010110100 *
1,
#381
0,
#382
b00000000000000000000001011010100 #
b00000000000000000000001011011000 $
b10110101 )
b00000000000000000000000010110101 *
1,
#383
0,
#384
b00000000000000000000001011011000 #
b00000000000000000000001011011100 $
b10110110 )
b00000000000000000000000010110110 *
1,
#385
0,
