rtl/audio_pwm_axi.sv
module audio_pwm_axi (
    input  logic        clk,
    input  logic        rst_n,

    // AXI4-Lite Write Address Channel (AW)
    input  logic [31:0] s_axi_awaddr,   // Write Target Address
    input  logic        s_axi_awvalid,  // Write Address Valid Strobe
    output logic        s_axi_awready,  // Peripheral Address Ready Flag

    // AXI4-Lite Write Data Channel (W)
    input  logic [31:0] s_axi_wdata,    // Inbound Data Word Payload
    input  logic        s_axi_wvalid,   // Write Data Valid Strobe
    output logic        s_axi_wready,   // Peripheral Data Ready Flag

    // AXI4-Lite Write Response Channel (B)
    output logic [1:0]  s_axi_bresp,    // Write Response Status (00 = OKAY)
    output logic        s_axi_bvalid,   // Response Status Valid Strobe
    input  logic        s_axi_bready,   // Manager Response Ready Flag

    output logic        audio_out       // Outbound physical PWM pin to speaker
);

    logic [7:0] sample_reg;
    logic [7:0] counter;

    // -------------------------------------------------------------------------
    // 1. AXI4-LITE WRITE CHANNEL HANDSHAKING ENGINE
    // -------------------------------------------------------------------------
    
    // The peripheral is ready to accept a new address/data transaction 
    // as long as it isn't currently holding an unacknowledged write response.
    assign s_axi_awready = !s_axi_bvalid;
    assign s_axi_wready  = !s_axi_bvalid;
    
    // Constant Response Code: 2'b00 represents an 'OKAY' transaction status
    assign s_axi_bresp   = 2'b00;

    // Bus Registration Control
    always_ff @(posedge clk or negedge rst_n) begin
        if (!rst_n) begin
            sample_reg   <= 8'h0;
            s_axi_bvalid <= 1'b0;
        end else begin
            // If both Address & Data channels validate simultaneously while ready:
            if (s_axi_awvalid && s_axi_wvalid && s_axi_awready && s_axi_wready) begin
                // Verify the address targeting matches our designated Audio address (0x400)
                if (s_axi_awaddr == 32'h400) begin
                    sample_reg <= s_axi_wdata[7:0]; // Capture lower byte payload
                end
                s_axi_bvalid <= 1'b1; // Raise valid response strobe to Manager
            end 
            // Drop response strobe once the Manager acknowledges receipt (bready)
            else if (s_axi_bready && s_axi_bvalid) begin
                s_axi_bvalid <= 1'b0;
            end
        end
    end

    // -------------------------------------------------------------------------
    // 2. YOUR ORIGINAL PWM GENERATION LOGIC
    // -------------------------------------------------------------------------
    always_ff @(posedge clk or negedge rst_n) begin
        if (!rst_n) begin
            counter <= 8'h0;
            audio_out <= 1'b0;
        end else begin
            counter   <= counter + 1;
            audio_out <= (counter < sample_reg); // Pulse active while counter is below sample window
        end
    end

endmodule

rtl/peripherals/timer_apb.sv
module timer (
    input  logic        clk,
    input  logic        rst_n,
    input  logic        we_i,      // Write Enable from CPU
    input  logic [31:0] wdata_i,   // Data from CPU (Sets the threshold)
    output logic        irq        // The interrupt signal
);
    logic [31:0] count;
    logic [31:0] threshold_reg;

    // Register the threshold value when the CPU writes to it
    always_ff @(posedge clk or negedge rst_n) begin
        if (!rst_n) 
            threshold_reg <= 32'hFFFF; // Default slow rate
        else if (we_i)
            threshold_reg <= wdata_i;
    end

    // Counter logic
    always_ff @(posedge clk or negedge rst_n) begin
        if (!rst_n) begin
            count <= 0;
            irq   <= 0;
        end else begin
            if (count >= threshold_reg) begin
                count <= 0;
                irq   <= 1; // Trigger interrupt
            end else begin
                count <= count + 1;
                irq   <= 0;
            end
        end
    end
endmodule

rtl/memory/instr_mem.sv
module instr_mem (
    input  logic [31:0] addr,
    output logic [31:0] instr
);
    // 1024 word memory (4KB)
    logic [31:0] rom [0:1023];

    // Load the compiled HEX file (we will generate this next)
    initial begin
        $readmemh("dv/hex/firmware.hex", rom);
    end

    // Instruction alignment (RISC-V instructions are 4-byte aligned)
    assign instr = rom[addr[11:2]]; 
endmodule

rtl/core/pc.sv
module pc(
    input  logic        clk,
    input  logic        rst_n, //reset
    input  logic        irq, //Trigger input 
    input  logic [31:0] d,   //The normal next address usually pc+4
    output logic [31:0] q,   //The current address the cpu is executing
    output logic [31:0] mepc //Machine exception program counter
);

    always_ff @(posedge clk or negedge rst_n) begin
        if(!rst_n) begin
            q <= 32'h0;     //start at address 0 on power
        end else if (irq) begin 
    mepc <= d; 
    q <= 32'h20; 
end else begin
            q <= d;  //otherwise,just go to next normal instruction
        end
    end
endmodule

rtl/core/alu.sv
module alu (
    input  logic [31:0] a, b,
    input  logic [3:0]  alu_ctrl,
    output logic [31:0] result,
    output logic        zero
);
    always_comb begin
        case (alu_ctrl)
            4'b0000: result = a & b;      // AND
            4'b0001: result = a | b;      // OR
            4'b0010: result = a + b;      // ADD
            4'b0110: result = a - b;      // SUB
            4'b0111: result = (a < b) ? 1 : 0; // SLT
            4'b1000: result = a * b;      // MUL
            default: result = 32'b0;
        endcase
        zero = (result == 32'b0);
    end
endmodule

rtl/core/regfile.sv
module regfile (
    input  logic        clk,
    input  logic        we,        // Write Enable
    input  logic [4:0]  rs1,       // Source Register 1 Address
    input  logic [4:0]  rs2,       // Source Register 2 Address
    input  logic [4:0]  rd,        // Destination Register Address
    input  logic [31:0] wd,        // Write Data
    output logic [31:0] rd1,       // Read Data 1
    output logic [31:0] rd2        // Read Data 2
);
    logic [31:0] rf [31:1]; // x1 to x31 (x0 is hardwired to 0)

    // Synchronous Write
    always_ff @(posedge clk) begin
        if (we && (rd != 5'b0)) begin
            rf[rd] <= wd;
        end
    end

    // Asynchronous Read
    assign rd1 = (rs1 == 5'b0) ? 32'b0 : rf[rs1];
    assign rd2 = (rs2 == 5'b0) ? 32'b0 : rf[rs2];

endmodule

rtl/core/control_unit.sv
module control_unit (
    input  logic [6:0] opcode,
    output logic       reg_write,
    output logic       alu_src,
    output logic       mem_to_reg,
    output logic [1:0] alu_op
);
    always_comb begin
        case (opcode)
            7'b0110011: begin // R-type (e.g., ADD)
                reg_write  = 1'b1;
                alu_src    = 1'b0;
                mem_to_reg = 1'b0;
                alu_op     = 2'b10;
            end
            7'b0010011: begin // I-type (e.g., ADDI)
                reg_write  = 1'b1;
                alu_src    = 1'b1;
                mem_to_reg = 1'b0;
                alu_op     = 2'b00;
            end
            7'b0000011: begin // Load (e.g., LW)
                reg_write  = 1'b1;
                alu_src    = 1'b1;
                mem_to_reg = 1'b1;
                alu_op     = 2'b00;
            end
            7'b0100011: begin // Store (e.g., SW to Audio)
                reg_write  = 1'b0;
                alu_src    = 1'b1;
                mem_to_reg = 1'b0;
                alu_op     = 2'b00;
            end
            default: begin
                reg_write  = 1'b0;
                alu_src    = 1'b0;
                mem_to_reg = 1'b0;
                alu_op     = 2'b00;
            end
        endcase
    end
endmodule

rtl/core/cpu_top.sv
module cpu_top (
    input  logic        clk,
    input  logic        rst_n,
    // External Memory/Peripheral Interface
    output logic [31:0] mem_addr,
    output logic [31:0] mem_wdata,
    output logic        mem_we,
    input  logic [31:0] mem_rdata
);

    // --- 1. Internal Wires (The Conveyor Belts) ---
    logic [31:0] pc_curr, pc_next;
    logic [31:0] instr;
    logic [31:0] reg_d1, reg_d2, alu_res, imm;
    logic [31:0] alu_mux_out, wb_data;
    
    // Control Signals (The Intercom System)
    logic        reg_we, alu_s, mem_reg;
    logic [1:0]  alu_op;
    logic [3:0]  alu_ctrl;
    logic [2:0]  funct3;
    logic [6:0]  funct7;

    // --- 2. Instruction Slicing (The Fine Print) ---
    assign instr  = mem_rdata; // Instruction fetched from memory
    assign funct3 = instr[14:12];
    assign funct7 = instr[31:25];

    // --- 3. ALU Decoder (The Translation Logic) ---
    // This looks at the Director's general order (alu_op) and the 
    // fine print (funct7) to trigger the Hardware Multiplier.
    always_comb begin
        case (alu_op)
            2'b00: alu_ctrl = 4'b0010; // Load/Store/I-Type: Default to ADD
            2'b01: alu_ctrl = 4'b0110; // Branch: Default to SUB
            2'b10: begin               // R-Type Math (ADD, SUB, MUL)
                // THE MULTIPLIER UPGRADE
                if (funct7 == 7'b0000001) begin
                    alu_ctrl = 4'b1000; // Found MUL signature!
                end else begin
                    case (funct3)
                        3'b000: alu_ctrl = (funct7[5]) ? 4'b0110 : 4'b0010; // SUB : ADD
                        3'b111: alu_ctrl = 4'b0000; // AND
                        3'b110: alu_ctrl = 4'b0001; // OR
                        default: alu_ctrl = 4'b0010;
                    endcase
                end
            end
            default: alu_ctrl = 4'b0010;
        endcase
    end

    // --- 4. Department Instantiations (Bolting the pieces in) ---

    // The Director (Main Control)
    control_unit u_ctrl (
        .opcode(instr[6:0]),
        .reg_write(reg_we),
        .alu_src(alu_s),
        .mem_to_reg(mem_reg),
        .alu_op(alu_op)
    );

    // The Workbench (Register File)
  // The Workbench (Register File)
    regfile u_regfile (
        .clk(clk),
        .we(reg_we),        // Fixed from .we3
        .rs1(instr[19:15]), // Fixed from .ra1
        .rs2(instr[24:20]), // Fixed from .ra2
        .rd(instr[11:7]),   // Fixed from .wa3
        .wd(wb_data),       // Fixed from .wd3
        .rd1(reg_d1),
        .rd2(reg_d2)
    );

    // The Factory Floor (Upgraded ALU with Multiplier)
    assign alu_mux_out = alu_s ? imm : reg_d2; 
    
    alu u_alu (
        .a(reg_d1),
        .b(alu_mux_out),
        .alu_ctrl(alu_ctrl), // Connected to the decoder logic above
        .result(alu_res),
        .zero() 
    );

    // --- 5. Final Routing (Delivery) ---
    assign wb_data   = mem_reg ? mem_rdata : alu_res; // Choose ALU result or Memory
    assign mem_addr  = alu_res;   // Address for Data Memory / Audio PWM
    assign mem_wdata = reg_d2;    // Data to write to Audio PWM
    assign mem_we    = (instr[6:0] == 7'b0100011); // Write enable if opcode is STORE

endmodule

rtl/audio_soc_top.sv
module audio_soc_top (
    input  logic clk,
    input  logic rst_n,
    output logic audio_out
);

    // --- 1. Interconnect Wires ---
    logic [31:0] pc_curr, pc_next;
    logic [31:0] instr;
    logic [31:0] cpu_mem_addr, cpu_mem_wdata;
    logic        cpu_mem_we;
    logic [31:0] cpu_mem_rdata;
    
    // Interrupt Lines
    logic        irq_signal; 
    logic [31:0] mepc_val;   

    // --- 2. AMBA AXI4-Lite Bus Channels ---
    logic [31:0] m_axi_awaddr;
    logic        m_axi_awvalid, m_axi_awready;
    logic [31:0] m_axi_wdata;
    logic        m_axi_wvalid,  m_axi_wready;
    logic [1:0]  m_axi_bresp;
    logic        m_axi_bvalid,  m_axi_bready;

    // --- 3. The AXI4-Lite Translation Bridge Logic ---
    assign m_axi_awaddr  = cpu_mem_addr;
    assign m_axi_wdata   = cpu_mem_wdata;
    
    // AXI Transactions fire ONLY when CPU drives write enable high at address 0x400
    assign m_axi_awvalid = (cpu_mem_we && (cpu_mem_addr == 32'h400));
    assign m_axi_wvalid  = (cpu_mem_we && (cpu_mem_addr == 32'h400));
    assign m_axi_bready  = 1'b1; // Core is instantly ready for write confirmation signals

    // --- 4. Unification Bus Multiplexer ---
    // Maps instruction fetch data streams into the CPU's shared input data channel
    assign cpu_mem_rdata = instr;

    // --- 5. Instantiating Your Core CPU Engine ---
    cpu_top u_core (
        .clk(clk),
        .rst_n(rst_n),
        .mem_addr(cpu_mem_addr),   // Connected to bridge target routing
        .mem_wdata(cpu_mem_wdata), // Connected to bridge data lanes
        .mem_we(cpu_mem_we),       // Connected to bridge handshake conditional gates
        .mem_rdata(cpu_mem_rdata)  // Connected to bus multiplexer
    );

    // --- 6. Execution Infrastructure ---

    // Program Counter Module
    pc u_pc (
        .clk(clk), 
        .rst_n(rst_n), 
        .d(pc_next),   
        .q(pc_curr),
        .irq(irq_signal), 
        .mepc(mepc_val)
    );
    
    // Instruction Memory Code Space Lookup
    instr_mem u_imem (
        .addr(pc_curr), 
        .instr(instr)
    );

    // --- 7. Peripherals ---

    // Programmable Timer Module (Direct MMIO Target at 0x500)
    timer u_timer (
        .clk(clk),
        .rst_n(rst_n),
        .we_i(cpu_mem_we && (cpu_mem_addr == 32'h500)),
        .wdata_i(cpu_mem_wdata),
        .irq(irq_signal)  
    );

    // Upgraded AXI Audio Output Block (Target at 0x400)
    audio_pwm_axi u_audio (
        .clk(clk),
        .rst_n(rst_n),
        .s_axi_awaddr(m_axi_awaddr),
        .s_axi_awvalid(m_axi_awvalid),
        .s_axi_awready(m_axi_awready),
        .s_axi_wdata(m_axi_wdata),
        .s_axi_wvalid(m_axi_wvalid),
        .s_axi_wready(m_axi_wready),
        .s_axi_bresp(m_axi_bresp),
        .s_axi_bvalid(m_axi_bvalid),
        .s_axi_bready(m_axi_bready),
        .audio_out(audio_out)
    );

    // Next PC Sequential Increment
    assign pc_next = pc_curr + 4;

endmodule

3.waveform_AXI_Peripheral_V1.1.vcd
$version Generated by VerilatedVcd $end
$timescale 1ps $end
 $scope module TOP $end
  $var wire 1 _ clk $end
  $var wire 1 ` rst_n $end
  $var wire 1 a audio_out $end
  $scope module audio_soc_top $end
   $var wire 1 _ clk $end
   $var wire 1 ` rst_n $end
   $var wire 1 a audio_out $end
   $var wire 32 # pc_curr [31:0] $end
   $var wire 32 $ pc_next [31:0] $end
   $var wire 32 L instr [31:0] $end
   $var wire 32 Y cpu_mem_addr [31:0] $end
   $var wire 32 Z cpu_mem_wdata [31:0] $end
   $var wire 1 M cpu_mem_we $end
   $var wire 32 L cpu_mem_rdata [31:0] $end
   $var wire 1 % irq_signal $end
   $var wire 32 & mepc_val [31:0] $end
   $var wire 32 Y m_axi_awaddr [31:0] $end
   $var wire 1 [ m_axi_awvalid $end
   $var wire 1 ' m_axi_awready $end
   $var wire 32 Z m_axi_wdata [31:0] $end
   $var wire 1 [ m_axi_wvalid $end
   $var wire 1 ' m_axi_wready $end
   $var wire 2 d m_axi_bresp [1:0] $end
   $var wire 1 ( m_axi_bvalid $end
   $var wire 1 e m_axi_bready $end
   $scope module u_audio $end
    $var wire 1 _ clk $end
    $var wire 1 ` rst_n $end
    $var wire 32 Y s_axi_awaddr [31:0] $end
    $var wire 1 [ s_axi_awvalid $end
    $var wire 1 ' s_axi_awready $end
    $var wire 32 Z s_axi_wdata [31:0] $end
    $var wire 1 [ s_axi_wvalid $end
    $var wire 1 ' s_axi_wready $end
    $var wire 2 d s_axi_bresp [1:0] $end
    $var wire 1 ( s_axi_bvalid $end
    $var wire 1 e s_axi_bready $end
    $var wire 1 a audio_out $end
    $var wire 8 ) sample_reg [7:0] $end
    $var wire 8 * counter [7:0] $end
   $upscope $end
   $scope module u_core $end
    $var wire 1 _ clk $end
    $var wire 1 ` rst_n $end
    $var wire 32 Y mem_addr [31:0] $end
    $var wire 32 Z mem_wdata [31:0] $end
    $var wire 1 M mem_we $end
    $var wire 32 L mem_rdata [31:0] $end
    $var wire 32 f pc_curr [31:0] $end
    $var wire 32 g pc_next [31:0] $end
    $var wire 32 L instr [31:0] $end
    $var wire 32 \ reg_d1 [31:0] $end
    $var wire 32 Z reg_d2 [31:0] $end
    $var wire 32 Y alu_res [31:0] $end
    $var wire 32 h imm [31:0] $end
    $var wire 32 ] alu_mux_out [31:0] $end
    $var wire 32 b wb_data [31:0] $end
    $var wire 1 N reg_we $end
    $var wire 1 O alu_s $end
    $var wire 1 P mem_reg $end
    $var wire 2 Q alu_op [1:0] $end
    $var wire 4 R alu_ctrl [3:0] $end
    $var wire 3 S funct3 [2:0] $end
    $var wire 7 T funct7 [6:0] $end
    $scope module u_alu $end
     $var wire 32 \ a [31:0] $end
     $var wire 32 ] b [31:0] $end
     $var wire 4 R alu_ctrl [3:0] $end
     $var wire 32 Y result [31:0] $end
     $var wire 1 ^ zero $end
    $upscope $end
    $scope module u_ctrl $end
     $var wire 7 U opcode [6:0] $end
     $var wire 1 N reg_write $end
     $var wire 1 O alu_src $end
     $var wire 1 P mem_to_reg $end
     $var wire 2 Q alu_op [1:0] $end
    $upscope $end
    $scope module u_regfile $end
     $var wire 1 _ clk $end
     $var wire 1 N we $end
     $var wire 5 V rs1 [4:0] $end
     $var wire 5 W rs2 [4:0] $end
     $var wire 5 X rd [4:0] $end
     $var wire 32 b wd [31:0] $end
     $var wire 32 \ rd1 [31:0] $end
     $var wire 32 Z rd2 [31:0] $end
     $var wire 32 - rf[1] [31:0] $end
     $var wire 32 . rf[2] [31:0] $end
     $var wire 32 / rf[3] [31:0] $end
     $var wire 32 0 rf[4] [31:0] $end
     $var wire 32 1 rf[5] [31:0] $end
     $var wire 32 2 rf[6] [31:0] $end
     $var wire 32 3 rf[7] [31:0] $end
     $var wire 32 4 rf[8] [31:0] $end
     $var wire 32 5 rf[9] [31:0] $end
     $var wire 32 6 rf[10] [31:0] $end
     $var wire 32 7 rf[11] [31:0] $end
     $var wire 32 8 rf[12] [31:0] $end
     $var wire 32 9 rf[13] [31:0] $end
     $var wire 32 : rf[14] [31:0] $end
     $var wire 32 ; rf[15] [31:0] $end
     $var wire 32 < rf[16] [31:0] $end
     $var wire 32 = rf[17] [31:0] $end
     $var wire 32 > rf[18] [31:0] $end
     $var wire 32 ? rf[19] [31:0] $end
     $var wire 32 @ rf[20] [31:0] $end
     $var wire 32 A rf[21] [31:0] $end
     $var wire 32 B rf[22] [31:0] $end
     $var wire 32 C rf[23] [31:0] $end
     $var wire 32 D rf[24] [31:0] $end
     $var wire 32 E rf[25] [31:0] $end
     $var wire 32 F rf[26] [31:0] $end
     $var wire 32 G rf[27] [31:0] $end
     $var wire 32 H rf[28] [31:0] $end
     $var wire 32 I rf[29] [31:0] $end
     $var wire 32 J rf[30] [31:0] $end
     $var wire 32 K rf[31] [31:0] $end
    $upscope $end
   $upscope $end
   $scope module u_imem $end
    $var wire 32 # addr [31:0] $end
    $var wire 32 L instr [31:0] $end
   $upscope $end
   $scope module u_pc $end
    $var wire 1 _ clk $end
    $var wire 1 ` rst_n $end
    $var wire 1 % irq $end
    $var wire 32 $ d [31:0] $end
    $var wire 32 # q [31:0] $end
    $var wire 32 & mepc [31:0] $end
   $upscope $end
   $scope module u_timer $end
    $var wire 1 _ clk $end
    $var wire 1 ` rst_n $end
    $var wire 1 c we_i $end
    $var wire 32 Z wdata_i [31:0] $end
    $var wire 1 % irq $end
    $var wire 32 + count [31:0] $end
    $var wire 32 , threshold_reg [31:0] $end
   $upscope $end
  $upscope $end
 $upscope $end
$enddefinitions $end


#0
b00000000000000000000000000000000 #
b00000000000000000000000000000100 $
0%
b00000000000000000000000000000000 &
1'
0(
b00000000 )
b00000000 *
b00000000000000000000000000000000 +
b00000000000000000000000000000000 ,
b00000000000000000000000000000000 -
b00000000000000000000000000000000 .
b00000000000000000000000000000000 /
b00000000000000000000000000000000 0
b00000000000000000000000000000000 1
b00000000000000000000000000000000 2
b00000000000000000000000000000000 3
b00000000000000000000000000000000 4
b00000000000000000000000000000000 5
b00000000000000000000000000000000 6
b00000000000000000000000000000000 7
b00000000000000000000000000000000 8
b00000000000000000000000000000000 9
b00000000000000000000000000000000 :
b00000000000000000000000000000000 ;
b00000000000000000000000000000000 <
b00000000000000000000000000000000 =
b00000000000000000000000000000000 >
b00000000000000000000000000000000 ?
b00000000000000000000000000000000 @
b00000000000000000000000000000000 A
b00000000000000000000000000000000 B
b00000000000000000000000000000000 C
b00000000000000000000000000000000 D
b00000000000000000000000000000000 E
b00000000000000000000000000000000 F
b00000000000000000000000000000000 G
b00000000000000000000000000000000 H
b00000000000000000000000000000000 I
b00000000000000000000000000000000 J
b00000000000000000000000000000000 K
b01000000000000000000001010010011 L
0M
1N
1O
0P
b00 Q
b0010 R
b000 S
b0100000 T
b0010011 U
b00000 V
b00000 W
b00101 X
b00000000000000000000000000000000 Y
b00000000000000000000000000000000 Z
0[
b00000000000000000000000000000000 \
b00000000000000000000000000000000 ]
1^
1_
0`
0a
b00000000000000000000000000000000 b
0c
b00 d
1e
b00000000000000000000000000000000 f
b00000000000000000000000000000000 g
b00000000000000000000000000000000 h
#1
0_
#2
b00000000000000001111111111111111 ,
1_
#3
0_
#4
1_
#5
0_
#6
1_
#7
0_
#8
1_
#9
0_
#10
1_
#11
0_
#12
1_
#13
0_
#14
1_
#15
0_
#16
1_
#17
0_
#18
1_
#19
0_
#20
1_
#21
0_
1`
#22
b00000000000000000000000000000100 #
b00000000000000000000000000001000 $
b00000001 *
b00000000000000000000000000000001 +
b00001111111100000000001100010011 L
b0000111 T
b11111 W
b00110 X
1_
#23
0_
#24
b00000000000000000000000000001000 #
b00000000000000000000000000001100 $
b00000010 *
b00000000000000000000000000000010 +
b00000000000000000000001110010011 L
b0000000 T
b00000 W
b00111 X
1_
#25
0_
#26
b00000000000000000000000000001100 #
b00000000000000000000000000010000 $
b00000011 *
b00000000000000000000000000000011 +
b00000000011000101010000000100011 L
1M
0N
b010 S
b0100011 U
b00101 V
b00110 W
b00000 X
1_
#27
0_
#28
b00000000000000000000000000010000 #
b00000000000000000000000000010100 $
b00000100 *
b00000000000000000000000000000100 +
b00000110010000000000111000010011 L
0M
1N
b000 S
b0000011 T
b0010011 U
b00000 V
b00100 W
b11100 X
1_
#29
0_
#30
b00000000000000000000000000010100 #
b00000000000000000000000000011000 $
b00000101 *
b00000000000000000000000000000101 +
b11111111111111100000111000010011 L
b1111111 T
b11100 V
b11111 W
1_
#31
0_
#32
b00000000000000000000000000011000 #
b00000000000000000000000000011100 $
b00000110 *
b00000000000000000000000000000110 +
b11111110000011100001111011100011 L
0N
0O
b001 S
b1100011 U
b00000 W
b11101 X
1_
#33
0_
#34
b00000000000000000000000000011100 #
b00000000000000000000000000100000 $
b00000111 *
b00000000000000000000000000000111 +
b00000000011100101010000000100011 L
1M
1O
b010 S
b0000000 T
b0100011 U
b00101 V
b00111 W
b00000 X
1_
#35
0_
#36
b00000000000000000000000000100000 #
b00000000000000000000000000100100 $
b00001000 *
b00000000000000000000000000001000 +
b00000110010000000000111000010011 L
0M
1N
b000 S
b0000011 T
b0010011 U
b00000 V
b00100 W
b11100 X
1_
#37
0_
#38
b00000000000000000000000000100100 #
b00000000000000000000000000101000 $
b00001001 *
b00000000000000000000000000001001 +
b11111111111111100000111000010011 L
b1111111 T
b11100 V
b11111 W
1_
#39
0_
#40
b00000000000000000000000000101000 #
b00000000000000000000000000101100 $
b00001010 *
b00000000000000000000000000001010 +
b11111110000011100001111011100011 L
0N
0O
b001 S
b1100011 U
b00000 W
b11101 X
1_
#41
0_
#42
b00000000000000000000000000101100 #
b00000000000000000000000000110000 $
b00001011 *
b00000000000000000000000000001011 +
b11111110000111111111000001101111 L
b111 S
b1101111 U
b11111 V
b00001 W
b00000 X
1_
#43
0_
#44
b00000000000000000000000000110000 #
b00000000000000000000000000110100 $
b00001100 *
b00000000000000000000000000001100 +
b00000000000000000000000000000000 L
b000 S
b0000000 T
b0000000 U
b00000 V
b00000 W
1_
#45
0_
#46
b00000000000000000000000000110100 #
b00000000000000000000000000111000 $
b00001101 *
b00000000000000000000000000001101 +
1_
#47
0_
#48
b00000000000000000000000000111000 #
b00000000000000000000000000111100 $
b00001110 *
b00000000000000000000000000001110 +
1_
#49
0_
#50
b00000000000000000000000000111100 #
b00000000000000000000000001000000 $
b00001111 *
b00000000000000000000000000001111 +
1_
#51
0_
#52
b00000000000000000000000001000000 #
b00000000000000000000000001000100 $
b00010000 *
b00000000000000000000000000010000 +
1_
#53
0_
#54
b00000000000000000000000001000100 #
b00000000000000000000000001001000 $
b00010001 *
b00000000000000000000000000010001 +
1_
#55
0_
#56
b00000000000000000000000001001000 #
b00000000000000000000000001001100 $
b00010010 *
b00000000000000000000000000010010 +
1_
#57
0_
#58
b00000000000000000000000001001100 #
b00000000000000000000000001010000 $
b00010011 *
b00000000000000000000000000010011 +
1_
#59
0_
#60
b00000000000000000000000001010000 #
b00000000000000000000000001010100 $
b00010100 *
b00000000000000000000000000010100 +
1_
#61
0_
#62
b00000000000000000000000001010100 #
b00000000000000000000000001011000 $
b00010101 *
b00000000000000000000000000010101 +
1_
#63
0_
#64
b00000000000000000000000001011000 #
b00000000000000000000000001011100 $
b00010110 *
b00000000000000000000000000010110 +
1_
#65
0_
#66
b00000000000000000000000001011100 #
b00000000000000000000000001100000 $
b00010111 *
b00000000000000000000000000010111 +
1_
#67
0_
#68
b00000000000000000000000001100000 #
b00000000000000000000000001100100 $
b00011000 *
b00000000000000000000000000011000 +
1_
#69
0_
#70
b00000000000000000000000001100100 #
b00000000000000000000000001101000 $
b00011001 *
b00000000000000000000000000011001 +
1_
#71
0_
#72
b00000000000000000000000001101000 #
b00000000000000000000000001101100 $
b00011010 *
b00000000000000000000000000011010 +
1_
#73
0_
#74
b00000000000000000000000001101100 #
b00000000000000000000000001110000 $
b00011011 *
b00000000000000000000000000011011 +
1_
#75
0_
#76
b00000000000000000000000001110000 #
b00000000000000000000000001110100 $
b00011100 *
b00000000000000000000000000011100 +
1_
#77
0_
#78
b00000000000000000000000001110100 #
b00000000000000000000000001111000 $
b00011101 *
b00000000000000000000000000011101 +
1_
#79
0_
#80
b00000000000000000000000001111000 #
b00000000000000000000000001111100 $
b00011110 *
b00000000000000000000000000011110 +
1_
#81
0_
#82
b00000000000000000000000001111100 #
b00000000000000000000000010000000 $
b00011111 *
b00000000000000000000000000011111 +
1_
#83
0_
#84
b00000000000000000000000010000000 #
b00000000000000000000000010000100 $
b00100000 *
b00000000000000000000000000100000 +
1_
#85
0_
#86
b00000000000000000000000010000100 #
b00000000000000000000000010001000 $
b00100001 *
b00000000000000000000000000100001 +
1_
#87
0_
#88
b00000000000000000000000010001000 #
b00000000000000000000000010001100 $
b00100010 *
b00000000000000000000000000100010 +
1_
#89
0_
#90
b00000000000000000000000010001100 #
b00000000000000000000000010010000 $
b00100011 *
b00000000000000000000000000100011 +
1_
#91
0_
#92
b00000000000000000000000010010000 #
b00000000000000000000000010010100 $
b00100100 *
b00000000000000000000000000100100 +
1_
#93
0_
#94
b00000000000000000000000010010100 #
b00000000000000000000000010011000 $
b00100101 *
b00000000000000000000000000100101 +
1_
#95
0_
#96
b00000000000000000000000010011000 #
b00000000000000000000000010011100 $
b00100110 *
b00000000000000000000000000100110 +
1_
#97
0_
#98
b00000000000000000000000010011100 #
b00000000000000000000000010100000 $
b00100111 *
b00000000000000000000000000100111 +
1_
#99
0_
#100
b00000000000000000000000010100000 #
b00000000000000000000000010100100 $
b00101000 *
b00000000000000000000000000101000 +
1_
#101
0_
#102
b00000000000000000000000010100100 #
b00000000000000000000000010101000 $
b00101001 *
b00000000000000000000000000101001 +
1_
#103
0_
#104
b00000000000000000000000010101000 #
b00000000000000000000000010101100 $
b00101010 *
b00000000000000000000000000101010 +
1_
#105
0_
#106
b00000000000000000000000010101100 #
b00000000000000000000000010110000 $
b00101011 *
b00000000000000000000000000101011 +
1_
#107
0_
#108
b00000000000000000000000010110000 #
b00000000000000000000000010110100 $
b00101100 *
b00000000000000000000000000101100 +
1_
#109
0_
#110
b00000000000000000000000010110100 #
b00000000000000000000000010111000 $
b00101101 *
b00000000000000000000000000101101 +
1_
#111
0_
#112
b00000000000000000000000010111000 #
b00000000000000000000000010111100 $
b00101110 *
b00000000000000000000000000101110 +
1_
#113
0_
#114
b00000000000000000000000010111100 #
b00000000000000000000000011000000 $
b00101111 *
b00000000000000000000000000101111 +
1_
#115
0_
#116
b00000000000000000000000011000000 #
b00000000000000000000000011000100 $
b00110000 *
b00000000000000000000000000110000 +
1_
#117
0_
#118
b00000000000000000000000011000100 #
b00000000000000000000000011001000 $
b00110001 *
b00000000000000000000000000110001 +
1_
#119
0_
#120
b00000000000000000000000011001000 #
b00000000000000000000000011001100 $
b00110010 *
b00000000000000000000000000110010 +
1_
#121
0_
#122
b00000000000000000000000011001100 #
b00000000000000000000000011010000 $
b00110011 *
b00000000000000000000000000110011 +
1_
#123
0_
#124
b00000000000000000000000011010000 #
b00000000000000000000000011010100 $
b00110100 *
b00000000000000000000000000110100 +
1_
#125
0_
#126
b00000000000000000000000011010100 #
b00000000000000000000000011011000 $
b00110101 *
b00000000000000000000000000110101 +
1_
#127
0_
#128
b00000000000000000000000011011000 #
b00000000000000000000000011011100 $
b00110110 *
b00000000000000000000000000110110 +
1_
#129
0_
#130
b00000000000000000000000011011100 #
b00000000000000000000000011100000 $
b00110111 *
b00000000000000000000000000110111 +
1_
#131
0_
#132
b00000000000000000000000011100000 #
b00000000000000000000000011100100 $
b00111000 *
b00000000000000000000000000111000 +
1_
#133
0_
#134
b00000000000000000000000011100100 #
b00000000000000000000000011101000 $
b00111001 *
b00000000000000000000000000111001 +
1_
#135
0_
#136
b00000000000000000000000011101000 #
b00000000000000000000000011101100 $
b00111010 *
b00000000000000000000000000111010 +
1_
#137
0_
#138
b00000000000000000000000011101100 #
b00000000000000000000000011110000 $
b00111011 *
b00000000000000000000000000111011 +
1_
#139
0_
#140
b00000000000000000000000011110000 #
b00000000000000000000000011110100 $
b00111100 *
b00000000000000000000000000111100 +
1_
#141
0_
#142
b00000000000000000000000011110100 #
b00000000000000000000000011111000 $
b00111101 *
b00000000000000000000000000111101 +
1_
#143
0_
#144
b00000000000000000000000011111000 #
b00000000000000000000000011111100 $
b00111110 *
b00000000000000000000000000111110 +
1_
#145
0_
#146
b00000000000000000000000011111100 #
b00000000000000000000000100000000 $
b00111111 *
b00000000000000000000000000111111 +
1_
#147
0_
#148
b00000000000000000000000100000000 #
b00000000000000000000000100000100 $
b01000000 *
b00000000000000000000000001000000 +
1_
#149
0_
#150
b00000000000000000000000100000100 #
b00000000000000000000000100001000 $
b01000001 *
b00000000000000000000000001000001 +
1_
#151
0_
#152
b00000000000000000000000100001000 #
b00000000000000000000000100001100 $
b01000010 *
b00000000000000000000000001000010 +
1_
#153
0_
#154
b00000000000000000000000100001100 #
b00000000000000000000000100010000 $
b01000011 *
b00000000000000000000000001000011 +
1_
#155
0_
#156
b00000000000000000000000100010000 #
b00000000000000000000000100010100 $
b01000100 *
b00000000000000000000000001000100 +
1_
#157
0_
#158
b00000000000000000000000100010100 #
b00000000000000000000000100011000 $
b01000101 *
b00000000000000000000000001000101 +
1_
#159
0_
#160
b00000000000000000000000100011000 #
b00000000000000000000000100011100 $
b01000110 *
b00000000000000000000000001000110 +
1_
#161
0_
